{"repo": {"timestamp": 1756737108000, "version": 20002, "name": "Taskwarrior Flutter Nightly Builds Repo", "icon": "icon.png", "address": "https://ccextractor.github.io/taskwarrior-flutter/repo", "webBaseUrl": "https://ccextractor.github.io/taskwarrior-flutter", "description": "This repo is for nightly builds of the Taskwarrior Flutter app. It is not meant for production use, but for testing the latest changes."}, "requests": {"install": [], "uninstall": []}, "apps": [{"authorName": "CCExtractor Development", "categories": ["taskwarrior-flutter"], "suggestedVersionCode": "2147483647", "issueTracker": "https://github.com/CCExtractor/taskwarrior-flutter/issues", "license": "Unknown", "name": "Taskwarrior Nightly", "sourceCode": "https://github.com/CCExtractor/taskwarrior-flutter", "summary": "Taskwarrior is Free and Open Source Software that manages your TODO list from the command line. It is flexible, fast, and unobtrusive. It does its job then gets out of your way. The CLI tool and other relevant documentation can be found at Taskwarrior. This project aims to build an app for Taskwarrior. It is your task management app across all platforms. It helps you manage your tasks and filter them as per your needs.", "webSite": "https://github.com/CCExtractor/taskwarrior-flutter", "added": 1756737106000, "packageName": "com.ccextractor.taskwarrior.nightly", "lastUpdated": 1756737108000}], "packages": {"com.ccextractor.taskwarrior.nightly": [{"added": 1756737108000, "apkName": "nightly.7.apk", "hash": "379e16385e4e4e2adbe8c50398cc6613d4861f0cd110286239c576023c871670", "hashType": "sha256", "minSdkVersion": 21, "nativecode": ["arm64-v8a", "armeabi-v7a", "x86", "x86_64"], "packageName": "com.ccextractor.taskwarrior.nightly", "sig": "1478ed41a8b1b1d449c82db07179da0a", "signer": "a56227052da647b836c0152da7aa02b184b473013c886593e064611bd72982d3", "size": 33201125, "targetSdkVersion": 33, "uses-permission": [["android.permission.INTERNET", null], ["android.permission.READ_EXTERNAL_STORAGE", null], ["android.permission.POST_NOTIFICATIONS", null], ["android.permission.WRITE_EXTERNAL_STORAGE", null], ["android.permission.MANAGE_EXTERNAL_STORAGE", null], ["android.permission.RECEIVE_BOOT_COMPLETED", null], ["android.permission.USE_EXACT_ALARM", null], ["android.permission.VIBRATE", null], ["android.permission.ACCESS_NETWORK_STATE", null], ["android.permission.WAKE_LOCK", null], ["android.permission.FOREGROUND_SERVICE", null], ["com.ccextractor.taskwarrior.nightly.DYNAMIC_RECEIVER_NOT_EXPORTED_PERMISSION", null]], "versionCode": 7, "versionName": "2.0.0-nightly"}, {"added": 1756737107000, "apkName": "nightly.6.apk", "hash": "3c3148e9e4a02b05fb5144cdcdc74e10c2c9f42d86014f270f54d32aef4ced24", "hashType": "sha256", "minSdkVersion": 21, "nativecode": ["arm64-v8a", "armeabi-v7a", "x86", "x86_64"], "packageName": "com.ccextractor.taskwarrior.nightly", "sig": "1478ed41a8b1b1d449c82db07179da0a", "signer": "a56227052da647b836c0152da7aa02b184b473013c886593e064611bd72982d3", "size": 33192279, "targetSdkVersion": 33, "uses-permission": [["android.permission.INTERNET", null], ["android.permission.READ_EXTERNAL_STORAGE", null], ["android.permission.POST_NOTIFICATIONS", null], ["android.permission.WRITE_EXTERNAL_STORAGE", null], ["android.permission.MANAGE_EXTERNAL_STORAGE", null], ["android.permission.RECEIVE_BOOT_COMPLETED", null], ["android.permission.USE_EXACT_ALARM", null], ["android.permission.VIBRATE", null], ["android.permission.ACCESS_NETWORK_STATE", null], ["android.permission.WAKE_LOCK", null], ["android.permission.FOREGROUND_SERVICE", null], ["com.ccextractor.taskwarrior.nightly.DYNAMIC_RECEIVER_NOT_EXPORTED_PERMISSION", null]], "versionCode": 6, "versionName": "2.0.0-nightly"}, {"added": 1756737106000, "apkName": "nightly.5.apk", "hash": "09476f412ae9b4a6297c2c3997bae88afdb917d95b1a08ba3ac67c82036ae861", "hashType": "sha256", "minSdkVersion": 21, "nativecode": ["arm64-v8a", "armeabi-v7a", "x86", "x86_64"], "packageName": "com.ccextractor.taskwarrior.nightly", "sig": "1478ed41a8b1b1d449c82db07179da0a", "signer": "a56227052da647b836c0152da7aa02b184b473013c886593e064611bd72982d3", "size": 33192280, "targetSdkVersion": 33, "uses-permission": [["android.permission.INTERNET", null], ["android.permission.READ_EXTERNAL_STORAGE", null], ["android.permission.POST_NOTIFICATIONS", null], ["android.permission.WRITE_EXTERNAL_STORAGE", null], ["android.permission.MANAGE_EXTERNAL_STORAGE", null], ["android.permission.RECEIVE_BOOT_COMPLETED", null], ["android.permission.USE_EXACT_ALARM", null], ["android.permission.VIBRATE", null], ["android.permission.ACCESS_NETWORK_STATE", null], ["android.permission.WAKE_LOCK", null], ["android.permission.FOREGROUND_SERVICE", null], ["com.ccextractor.taskwarrior.nightly.DYNAMIC_RECEIVER_NOT_EXPORTED_PERMISSION", null]], "versionCode": 5, "versionName": "2.0.0-nightly"}]}}